commons/RabbitHeartbeat.py
commons/__init__.py
commons/baan_repository.py
commons/constants.py
commons/json_parser.py
commons/models.py
commons/mysql_repository.py
commons/utils.py
mangata_workflow_commons-0.0.9.dist-info/METADATA
mangata_workflow_commons-0.0.9.dist-info/WHEEL
mangata_workflow_commons-0.0.9.dist-info/top_level.txt
mangata_workflow_commons-0.0.9.dist-info/zip-safe
mangata_workflow_commons-0.0.9.dist-info/RECORD
