Metadata-Version: 2.1
Name: mangata-workflow-commons
Version: 0.0.9
Summary: Data processing and and specific utils modules in Python
Home-page: http://github.com/pip-services3-python/pip-services3-data-python
Author: Jack Camier, Anastas Fonotov
Author-email: Jacques.Camier@balfour.com, afonotov@cbi-inet.com
License: MIT
Platform: any
Classifier: Programming Language :: Python :: 3.7
Requires-Dist: sqlalchemy
Requires-Dist: cx-oracle
Requires-Dist: pyinstaller
Requires-Dist: requests
Requires-Dist: zeep
Requires-Dist: oauth2
Requires-Dist: pika
Requires-Dist: pysftp
Requires-Dist: pymysql
Requires-Dist: python-dateutil
